{
    "rub2rsd": {
        "bank": {
            "current": 1.254830719401795,
            "sparkline_full": "                          1.26    \n  ▁▃▄▄▂▂▂▂▃▇▇▆▆▇▇▇▆▆▆▇▆▆▆▆▆█▇▇▇▇  \n 1.20                             "
        },
        "korona": {
            "current": 1.2112460905541065,
            "diff_percent": -3.4733472948818287
        },
        "crypto": {
            "current": 1.297356936111754,
            "diff_percent": 3.3890002892368085
        },
        "forex": {
            "current": 1.344241246271073,
            "diff_percent": 7.125305866906266
        }
    },
    "rub2eur": {
        "bank": {
            "current": 0.010806137886319428,
            "sparkline_full": "                          92.1    \n  ▁▃▄▄▂▂▂▂▄▇▆▆▆▆▆▆▇▇▆▆▆▆▅▅▆█▇▇▇▇  \n 96.4                             "
        },
        "korona": {
            "current": 0.010374698848429178,
            "diff_percent": -3.9925368566363777
        },
        "crypto": {
            "current": 0.011122387479543404,
            "diff_percent": 2.926573735694676
        },
        "forex": {
            "current": 0.011413566363309596,
            "diff_percent": 5.6211431260670155
        }
    },
    "rub2usd": {
        "bank": {
            "current": 0.012281994595922378,
            "sparkline_full": "                           81.0   \n  ▁▃▄▄▂▂▂▂▃▄▅▅▄▄▄▅▅▅▆▆▇▇▆▆▆▇█▇▇▇  \n 85.1                             "
        },
        "korona": {
            "current": 0.011326105575579408,
            "diff_percent": -7.782848403632461
        },
        "crypto": {
            "current": 0.012615470623684446,
            "diff_percent": 2.715161818038757
        },
        "forex": {
            "current": 0.012719879008510872,
            "diff_percent": 3.5652548872955188
        }
    },
    "xdr": {
        "rub2xdr": {
            "current_rate": 0.009775210392964041,
            "sparkline": "▁▁▂▂▂▁▁▁▂▂▃▃▂▅▅▃▃▃▃▃▃▄▃▂▂▄▅▅██"
        },
        "usd2xdr": {
            "current_rate": 0.754425,
            "sparkline": "▃▃▃▃▃▃▃▃▃▃▃▃▃▆▆▄▄▃▃▃▃▃▃▃▃▃▃▃▆▆"
        },
        "eur2xdr": {
            "current_rate": 0.8564553866693005,
            "sparkline": "▃▃▃▄▃▃▃▃▂▂▃▃▃▆▆▄▄▄▃▄▄▄▃▃▃▃▄▄▇▇"
        },
        "cny2xdr": {
            "current_rate": 0.10478416067112975,
            "sparkline": "▂▂▂▃▃▃▃▃▃▃▃▃▃▆▆▄▄▄▃▄▄▄▃▃▃▃▃▃▇▇"
        },
        "rsd2xdr": {
            "current_rate": 0.0072719167188780185,
            "sparkline": "▄▄▄▄▄▄▄▄▃▂▂▂▃▆▆▄▄▄▄▄▄▄▄▃▃▃▄▄▇▇"
        }
    },
    "neer": {
        "rub": {
            "current_rate": 100.34958621437998,
            "sparkline": "▁▂▁▃▃▄▁▁▄▄▄▅▅▄▄▄▄▄▅▅▅▅▄▄▄▅████"
        },
        "usd": {
            "current_rate": 104.94903159142117,
            "sparkline": "▅▄▄▄▅▅▅▅▆▆▅▅▅▅▅▅▅▄▄▄▃▃▃▃▄▄▄▄▄▄"
        },
        "eur": {
            "current_rate": 108.14818788200202,
            "sparkline": "▅▅▅▅▅▅▅▅▄▄▄▄▄▄▄▅▄▅▅▄▅▅▅▅▅▄▅▅▅▅"
        },
        "cny": {
            "current_rate": 103.93103810875444,
            "sparkline": "▄▃▄▄▄▄▄▄▆▆▅▅▅▅▅▅▅▄▄▄▄▄▄▄▄▅▄▄▄▄"
        },
        "rsd": {
            "current_rate": 109.34073758936196,
            "sparkline": "▅▅▅▅▅▄▆▆▆▄▃▄▄▄▄▄▅▅▄▅▄▄▅▅▄▄▄▄▄▄"
        }
    },
    "update_time": "2025-06-02 02:21:32",
    "update_time_display": "02.06 02:21"
}