{
    "rub2rsd": {
        "bank": {
            "current": 1.3386265658988514,
            "sparkline_full": "   1.36                           \n  ▄▆█▇█▇▇▇▇▆▇▇▇▇▆▅▃▁▂▃▃▄▅▆▆▆▅▅▅▆  \n                  1.30            "
        },
        "korona": {
            "current": 1.2972363833800429,
            "diff_percent": -3.091988727342802
        },
        "crypto": {
            "current": 1.406043589858925,
            "diff_percent": 5.036283133586613
        },
        "forex": {
            "current": 1.402102738050351,
            "diff_percent": 4.741887974476067
        }
    },
    "rub2eur": {
        "bank": {
            "current": 0.011519410206197442,
            "sparkline_full": "   85.7                           \n  ▄▆█████▇▆▆████▇▅▃▁▂▂▂▃▅▆▆▆▅▅▅▆  \n                  89.4            "
        },
        "korona": {
            "current": 0.011106475885103106,
            "diff_percent": -3.5846828414199257
        },
        "crypto": {
            "current": 0.012074795990709809,
            "diff_percent": 4.821303995351856
        },
        "forex": {
            "current": 0.01194496251783098,
            "diff_percent": 3.69421961729074
        }
    },
    "rub2usd": {
        "bank": {
            "current": 0.013374348000534974,
            "sparkline_full": "            73.7                  \n  ▄▇█▇▇▇▇▇▇▇████▇▅▃▁▂▂▂▂▅▅▅▅▅▅▅▅  \n                  76.9            "
        },
        "korona": {
            "current": 0.0126128962895483,
            "diff_percent": -5.69337444304736
        },
        "crypto": {
            "current": 0.01399104031883873,
            "diff_percent": 4.611008463957178
        },
        "forex": {
            "current": 0.013802374836614388,
            "diff_percent": 3.200356653365777
        }
    },
    "xdr": {
        "rub2xdr": {
            "current_rate": 0.009750162148922178,
            "sparkline": "▂▃▄▅█▅▃▄▃▃▄▄▄▄▃▂▁▁▁▁▁▂▃▄▃▃▂▂▂▃"
        },
        "usd2xdr": {
            "current_rate": 0.703697,
            "sparkline": "▂▂▂▃▇▄▂▂▂▂▂▂▂▂▂▂▂▂▂▂▂▃▃▃▃▃▃▃▃▃"
        },
        "eur2xdr": {
            "current_rate": 0.816257241022524,
            "sparkline": "▃▃▂▃▇▄▃▃▂▃▃▃▃▃▂▃▂▃▂▂▂▃▃▃▃▃▃▃▃▃"
        },
        "cny2xdr": {
            "current_rate": 0.10409103011656116,
            "sparkline": "▂▂▂▃▇▄▂▂▂▂▂▂▂▂▂▃▃▃▃▃▃▃▃▃▃▃▃▃▃▃"
        },
        "rsd2xdr": {
            "current_rate": 0.006953956999242404,
            "sparkline": "▃▃▂▃▇▄▃▃▃▃▃▃▃▃▂▃▂▃▂▂▂▃▃▃▃▃▃▃▃▃"
        }
    },
    "neer": {
        "rub": {
            "current_rate": 105.88183937579775,
            "sparkline": "▃▅▇██▆▆█▆▆█▇▆▆▇▆▄▃▁▂▂▁▃▆▅▅▄▄▄▄"
        },
        "usd": {
            "current_rate": 102.53154363892098,
            "sparkline": "▄▄▄▄▄▅▅▄▄▄▄▄▄▄▄▄▄▄▄▅▅▅▄▅▅▅▅▅▄▅"
        },
        "eur": {
            "current_rate": 108.85040601295752,
            "sparkline": "▅▅▅▄▄▄▄▄▄▅▄▄▄▄▄▅▄▅▅▄▄▄▄▄▄▄▄▄▄▄"
        },
        "cny": {
            "current_rate": 112.22712196653802,
            "sparkline": "▄▄▄▄▅▃▃▄▄▄▅▅▃▃▅▅▅▅▆▅▅▆▆▄▅▄▄▄▄▄"
        },
        "rsd": {
            "current_rate": 109.34287854753151,
            "sparkline": "▇█▇▇▇▂▂▇▇▇▇▇▂▂▇▇▇▇▆▂▂▇▆▂▂▂▂▂▁▂"
        }
    },
    "specific_rates": {
        "rub_kzt_bank": 6.56,
        "rub_kzt_crypto": 6.876596316709236,
        "kzt_rsd_bank": 0.2044679555265476,
        "rsd_eur_cash": 0.00844880027036161,
        "eur_rsd_cash": 116.8,
        "rsd_usd_cash": 0.009722897423432181,
        "usd_rsd_cash": 99.3,
        "eur_usd_exch": 1.1599555505033046,
        "usd_kzt_bank": 484.5
    },
    "update_time": "2026-06-16 16:05:46",
    "update_time_display": "16.06 16:05"
}