{
    "rub2rsd": {
        "bank": {
            "current": 1.277355906884103,
            "sparkline_full": "       1.34                       \n  ▅▅▆▆▆▇▇▇▇▇▇▇▇ ▆   ▇▇▆▆▄▂▂▂▂▂ ▃  \n                        1.26      "
        },
        "korona": {
            "current": 1.2296463265547746,
            "diff_percent": -3.735026398845091
        },
        "crypto": {
            "current": 1.3612422411607537,
            "diff_percent": 6.5671856860377655
        },
        "forex": {
            "current": 1.3252480393702974,
            "diff_percent": 3.7493178078316003
        }
    },
    "rub2eur": {
        "bank": {
            "current": 0.010862480990658266,
            "sparkline_full": "        86.5                      \n  ▅▅▅▅▆▇███▇▇▇▇ ▇▇▇▇▇▆▆▆▃▁▁▂▂▂▃▃  \n                         93.7     "
        },
        "korona": {
            "current": 0.010527793891736085,
            "diff_percent": -3.081129432677602
        },
        "crypto": {
            "current": 0.011532809478750978,
            "diff_percent": 6.171044061381503
        },
        "forex": {
            "current": 0.011295124546538103,
            "diff_percent": 3.9829165754297784
        }
    },
    "rub2usd": {
        "bank": {
            "current": 0.012448649321548612,
            "sparkline_full": "       74.8                       \n  ▆▆▇▇▇████████ ▇▇▇▇▇▆▅▅▂▁▁▁▁▁▂▂  \n                         82.1     "
        },
        "korona": {
            "current": 0.011812975071547962,
            "diff_percent": -5.106371250255219
        },
        "crypto": {
            "current": 0.01319072647622095,
            "diff_percent": 5.961105783482893
        },
        "forex": {
            "current": 0.01283214400745291,
            "diff_percent": 3.08061281186923
        }
    },
    "xdr": {
        "rub2xdr": {
            "current_rate": 0.009226469128706486,
            "sparkline": "▄▄▄▄▅▆▇▆▆▆▆▆▆ ▅▅██▅▅▅▄▂▁▁▁▁▁▂▂"
        },
        "usd2xdr": {
            "current_rate": 0.713237,
            "sparkline": "▃▃▃▃▃▃▃▃▃▃▃▃▃ ▃▃▆▆▄▄▄▄▄▄▄▄▄▄▄▄"
        },
        "eur2xdr": {
            "current_rate": 0.816854129469015,
            "sparkline": "▄▃▃▃▄▄▄▄▄▄▄▄▄ ▃▃▆▆▄▃▃▄▄▄▄▄▄▄▄▄"
        },
        "cny2xdr": {
            "current_rate": 0.10513827058580735,
            "sparkline": "▃▃▃▃▃▃▃▃▃▃▃▃▃ ▃▃▆▆▄▄▄▄▄▄▄▄▄▄▄▄"
        },
        "rsd2xdr": {
            "current_rate": 0.006962069631199394,
            "sparkline": "▄▃▃▃▄▄▄▄▄▄▄▄▄ ▃▃▆▆▄▃▃▄▄▄▄▄▄▄▄▄"
        }
    },
    "neer": {
        "rub": {
            "current_rate": 99.88156536637524,
            "sparkline": "▆▅▆▆▅▆███▇▇█▇█▇▇▇▇▇▇▆▆▄▂▁▄▂▁▂▂"
        },
        "usd": {
            "current_rate": 103.58184068279814,
            "sparkline": "▄▄▅▅▄▄▄▄▄▄▄▄▄▄▄▄▅▅▄▅▅▅▅▅▅▅▅▅▅▅"
        },
        "eur": {
            "current_rate": 108.6147671797951,
            "sparkline": "▅▅▄▅▅▅▅▅▅▅▅▅▅▅▄▄▄▄▄▄▄▄▄▄▄▄▄▅▄▄"
        },
        "cny": {
            "current_rate": 113.04897444392448,
            "sparkline": "▄▄▄▄▄▄▄▅▄▄▄▄▄▄▅▅▄▄▅▅▅▅▅▄▄▅▅▄▄▄"
        },
        "rsd": {
            "current_rate": 109.42039233259328,
            "sparkline": "▆▆▃▃▆▆▆▆▆▃▃▆▆▆▆▆▃▃▅▆▆▆▆▃▃▆▆▃▃▃"
        }
    },
    "specific_rates": {
        "rub_kzt_bank": 5.92,
        "rub_kzt_crypto": 6.285381165919283,
        "kzt_rsd_bank": 0.21657274320000003,
        "rsd_eur_cash": 0.00844880027036161,
        "eur_rsd_cash": 116.8,
        "rsd_usd_cash": 0.00960680710903726,
        "usd_rsd_cash": 100.39285714285714,
        "eur_usd_exch": 1.145277277355234,
        "usd_kzt_bank": 469.5
    },
    "conversion_rates": {
        "rub_usd": {
            "rub_to_usd": [
                0.012448649321548612,
                0.012360939431396786
            ],
            "usd_to_rub": [
                74.96,
                76.2
            ]
        },
        "rub_eur": {
            "rub_to_eur": [
                0.010862480990658266,
                0.010799136069114472
            ],
            "eur_to_rub": [
                85.81,
                87.5
            ]
        },
        "rub_kzt": {
            "rub_to_kzt": [
                5.92,
                5.847953216374268
            ],
            "kzt_to_rub": [
                0.1594896331738437,
                0.16
            ]
        },
        "rub_rsd": {
            "rub_to_rsd": [
                1.3283608415
            ],
            "rsd_to_rub": [
                0.7528074968476102
            ]
        },
        "usd_eur": {
            "usd_to_eur": [
                0.8655760408551891
            ],
            "eur_to_usd": [
                1.1353
            ]
        },
        "usd_kzt": {
            "usd_to_kzt": [
                469.5
            ],
            "kzt_to_usd": [
                0.002098635886673662
            ]
        },
        "usd_rsd": {
            "usd_to_rsd": [
                102.61
            ],
            "rsd_to_usd": [
                0.009745638826625085
            ]
        },
        "eur_kzt": {
            "eur_to_kzt": [
                538.0
            ],
            "kzt_to_eur": [
                0.001834862385321101
            ]
        },
        "eur_rsd": {
            "eur_to_rsd": [
                117.73459630630002
            ],
            "rsd_to_eur": [
                0.008493680119294635
            ]
        },
        "kzt_rsd": {
            "kzt_to_rsd": [
                0.21657274320000003
            ],
            "rsd_to_kzt": [
                4.617386219633939
            ]
        },
        "eur_usd_forex": {
            "eur_to_usd": [
                1.145277277355234
            ],
            "usd_to_eur": [
                0.873151
            ]
        }
    },
    "update_time": "2026-07-03 12:06:47",
    "update_time_display": "03.07 12:06"
}