{
  "USD-forex": {
    "GBP-forex": [
      {
        "name": "OpenExchangeRates",
        "rate": 0.747915,
        "direct": true,
        "datetime": "2026-06-11T03:05:48.908090"
      }
    ],
    "CNY-forex": [
      {
        "name": "OpenExchangeRates",
        "rate": 6.7737,
        "direct": true,
        "datetime": "2026-06-11T03:05:48.908090"
      }
    ],
    "EUR-forex": [
      {
        "name": "OpenExchangeRates",
        "rate": 0.866371,
        "direct": true,
        "datetime": "2026-06-11T03:05:48.908090"
      }
    ],
    "JPY-forex": [
      {
        "name": "OpenExchangeRates",
        "rate": 160.51859091,
        "direct": true,
        "datetime": "2026-06-11T03:05:48.908090"
      }
    ],
    "RUB-forex": [
      {
        "name": "OpenExchangeRates",
        "rate": 72.247862,
        "direct": true,
        "datetime": "2026-06-11T03:05:48.908090"
      },
      {
        "name": "MOEX Indicative",
        "rate": 71.7892,
        "direct": true,
        "datetime": "2026-06-11T03:05:05.507134"
      }
    ],
    "RSD-forex": [
      {
        "name": "OpenExchangeRates",
        "rate": 101.696824,
        "direct": true,
        "datetime": "2026-06-11T03:05:48.908090"
      }
    ],
    "KZT-forex": [
      {
        "name": "OpenExchangeRates",
        "rate": 488.018849,
        "direct": true,
        "datetime": "2026-06-11T03:05:48.908090"
      }
    ],
    "XDR-forex": [
      {
        "name": "OpenExchangeRates",
        "rate": 0.706825,
        "direct": true,
        "datetime": "2026-06-11T03:05:48.908090"
      }
    ]
  },
  "GBP-forex": {
    "USD-forex": [
      {
        "name": "OpenExchangeRates",
        "rate": 0.747915,
        "direct": false,
        "datetime": "2026-06-11T03:05:48.908090"
      }
    ],
    "RUB-forex": [
      {
        "name": "MOEX Indicative",
        "rate": 96.1832,
        "direct": true,
        "datetime": "2026-06-11T03:05:05.507134"
      }
    ]
  },
  "CNY-forex": {
    "USD-forex": [
      {
        "name": "OpenExchangeRates",
        "rate": 6.7737,
        "direct": false,
        "datetime": "2026-06-11T03:05:48.908090"
      }
    ],
    "RUB-forex": [
      {
        "name": "MOEX Indicative",
        "rate": 10.585,
        "direct": true,
        "datetime": "2026-06-11T03:05:05.507134"
      }
    ]
  },
  "EUR-forex": {
    "USD-forex": [
      {
        "name": "OpenExchangeRates",
        "rate": 0.866371,
        "direct": false,
        "datetime": "2026-06-11T03:05:48.908090"
      }
    ],
    "RUB-forex": [
      {
        "name": "MOEX Indicative",
        "rate": 83.0816,
        "direct": true,
        "datetime": "2026-06-11T03:05:05.507134"
      }
    ]
  },
  "JPY-forex": {
    "USD-forex": [
      {
        "name": "OpenExchangeRates",
        "rate": 160.51859091,
        "direct": false,
        "datetime": "2026-06-11T03:05:48.908090"
      }
    ],
    "RUB-forex": [
      {
        "name": "MOEX Indicative",
        "rate": 2.2345869366047686,
        "direct": false,
        "datetime": "2026-06-11T03:05:05.507134"
      }
    ]
  },
  "RUB-forex": {
    "USD-forex": [
      {
        "name": "OpenExchangeRates",
        "rate": 72.247862,
        "direct": false,
        "datetime": "2026-06-11T03:05:48.908090"
      },
      {
        "name": "MOEX Indicative",
        "rate": 71.7892,
        "direct": false,
        "datetime": "2026-06-11T03:05:05.507134"
      }
    ],
    "EUR-forex": [
      {
        "name": "MOEX Indicative",
        "rate": 83.0816,
        "direct": false,
        "datetime": "2026-06-11T03:05:05.507134"
      }
    ],
    "KZT-forex": [
      {
        "name": "MOEX Indicative",
        "rate": 6.4935064935064934,
        "direct": true,
        "datetime": "2026-06-11T03:05:05.507134"
      }
    ],
    "GBP-forex": [
      {
        "name": "MOEX Indicative",
        "rate": 96.1832,
        "direct": false,
        "datetime": "2026-06-11T03:05:05.507134"
      }
    ],
    "CNY-forex": [
      {
        "name": "MOEX Indicative",
        "rate": 10.585,
        "direct": false,
        "datetime": "2026-06-11T03:05:05.507134"
      }
    ],
    "JPY-forex": [
      {
        "name": "MOEX Indicative",
        "rate": 2.2345869366047686,
        "direct": true,
        "datetime": "2026-06-11T03:05:05.507134"
      }
    ]
  },
  "RSD-forex": {
    "USD-forex": [
      {
        "name": "OpenExchangeRates",
        "rate": 101.696824,
        "direct": false,
        "datetime": "2026-06-11T03:05:48.908090"
      }
    ]
  },
  "KZT-forex": {
    "USD-forex": [
      {
        "name": "OpenExchangeRates",
        "rate": 488.018849,
        "direct": false,
        "datetime": "2026-06-11T03:05:48.908090"
      }
    ],
    "RUB-forex": [
      {
        "name": "MOEX Indicative",
        "rate": 6.4935064935064934,
        "direct": false,
        "datetime": "2026-06-11T03:05:05.507134"
      }
    ]
  },
  "RUB-bank": {
    "USD-bank": [
      {
        "name": "Cifra RU",
        "rate": 75.8,
        "direct": false,
        "datetime": "2026-06-11T03:05:47.120880"
      },
      {
        "name": "Freedom KZ",
        "rate": 74.96,
        "direct": false,
        "datetime": "2026-06-11T03:05:48.915330"
      }
    ],
    "EUR-bank": [
      {
        "name": "Cifra RU",
        "rate": 87.0,
        "direct": false,
        "datetime": "2026-06-11T03:05:47.120880"
      },
      {
        "name": "Freedom KZ",
        "rate": 86.72,
        "direct": false,
        "datetime": "2026-06-11T03:05:48.915330"
      }
    ],
    "KZT-bank": [
      {
        "name": "Cifra RU",
        "rate": 0.1555,
        "direct": false,
        "datetime": "2026-06-11T03:05:47.120880"
      },
      {
        "name": "Freedom KZ",
        "rate": 6.55,
        "direct": true,
        "datetime": "2026-06-11T03:05:48.915330"
      }
    ],
    "USD-crypto": [
      {
        "name": "Bybit P2P",
        "rate": 74.605,
        "direct": false,
        "datetime": "2026-06-11T03:05:08.502235"
      }
    ],
    "EUR-cash": [
      {
        "name": "Korona Pay",
        "rate": 89.127248,
        "direct": false,
        "datetime": "2026-06-11T03:05:48.265201"
      }
    ],
    "RSD-bank": [
      {
        "name": "Visa Payment",
        "rate": 1.3812911914621746,
        "direct": true,
        "datetime": "2026-06-11T00:20:07.038059+00:00"
      }
    ]
  },
  "USD-bank": {
    "RUB-bank": [
      {
        "name": "Cifra RU",
        "rate": 71.6,
        "direct": true,
        "datetime": "2026-06-11T03:05:47.120880"
      },
      {
        "name": "Freedom KZ",
        "rate": 70.36,
        "direct": true,
        "datetime": "2026-06-11T03:05:48.915330"
      }
    ],
    "KZT-bank": [
      {
        "name": "Freedom KZ",
        "rate": 485.0,
        "direct": true,
        "datetime": "2026-06-11T03:05:48.915330"
      }
    ],
    "EUR-bank": [
      {
        "name": "Freedom KZ",
        "rate": 1.164,
        "direct": false,
        "datetime": "2026-06-11T03:05:48.915330"
      }
    ],
    "RSD-bank": [
      {
        "name": "Visa Payment",
        "rate": 100.49504966912558,
        "direct": true,
        "datetime": "2026-06-11T00:20:05.273481+00:00"
      }
    ]
  },
  "EUR-bank": {
    "RUB-bank": [
      {
        "name": "Cifra RU",
        "rate": 82.2,
        "direct": true,
        "datetime": "2026-06-11T03:05:47.120880"
      },
      {
        "name": "Freedom KZ",
        "rate": 81.3,
        "direct": true,
        "datetime": "2026-06-11T03:05:48.915330"
      }
    ],
    "KZT-bank": [
      {
        "name": "Freedom KZ",
        "rate": 561.0,
        "direct": true,
        "datetime": "2026-06-11T03:05:48.915330"
      }
    ],
    "USD-bank": [
      {
        "name": "Freedom KZ",
        "rate": 1.144,
        "direct": true,
        "datetime": "2026-06-11T03:05:48.915330"
      }
    ],
    "RSD-bank": [
      {
        "name": "Visa Payment",
        "rate": 115.87090775818298,
        "direct": true,
        "datetime": "2026-06-11T00:20:05.677696+00:00"
      }
    ]
  },
  "KZT-bank": {
    "RUB-bank": [
      {
        "name": "Cifra RU",
        "rate": 0.146,
        "direct": true,
        "datetime": "2026-06-11T03:05:47.120880"
      },
      {
        "name": "Freedom KZ",
        "rate": 6.9,
        "direct": false,
        "datetime": "2026-06-11T03:05:48.915330"
      }
    ],
    "USD-crypto": [
      {
        "name": "Bybit P2P",
        "rate": 515.0714285714286,
        "direct": true,
        "datetime": "2026-06-11T03:05:08.502235"
      }
    ],
    "USD-bank": [
      {
        "name": "Freedom KZ",
        "rate": 492.0,
        "direct": false,
        "datetime": "2026-06-11T03:05:48.915330"
      }
    ],
    "EUR-bank": [
      {
        "name": "Freedom KZ",
        "rate": 568.0,
        "direct": false,
        "datetime": "2026-06-11T03:05:48.915330"
      }
    ],
    "RSD-bank": [
      {
        "name": "Visa Payment",
        "rate": 0.2060338065950625,
        "direct": true,
        "datetime": "2026-06-11T00:20:06.076893+00:00"
      }
    ]
  },
  "EUR-cash": {
    "RSD-cash": [
      {
        "name": "Cash Exch",
        "rate": 116.8,
        "direct": true,
        "datetime": "2026-06-11T03:05:50.415938"
      }
    ]
  },
  "RSD-cash": {
    "EUR-cash": [
      {
        "name": "Cash Exch",
        "rate": 118.35999999999999,
        "direct": false,
        "datetime": "2026-06-11T03:05:50.415938"
      }
    ],
    "USD-cash": [
      {
        "name": "Cash Exch",
        "rate": 103.01666666666667,
        "direct": false,
        "datetime": "2026-06-11T03:05:50.415938"
      }
    ],
    "RUB-cash": [
      {
        "name": "Cash Exch",
        "rate": 1.43,
        "direct": false,
        "datetime": "2026-06-11T03:05:50.415938"
      }
    ]
  },
  "USD-cash": {
    "RSD-cash": [
      {
        "name": "Cash Exch",
        "rate": 99.41666666666667,
        "direct": true,
        "datetime": "2026-06-11T03:05:50.415938"
      }
    ]
  },
  "RUB-cash": {
    "RSD-cash": [
      {
        "name": "Cash Exch",
        "rate": 1.26,
        "direct": true,
        "datetime": "2026-06-11T03:05:50.415938"
      }
    ]
  },
  "USD-crypto": {
    "RUB-bank": [
      {
        "name": "Bybit P2P",
        "rate": 83.03,
        "direct": true,
        "datetime": "2026-06-11T03:05:08.502235"
      }
    ],
    "KZT-bank": [
      {
        "name": "Bybit P2P",
        "rate": 498.48999999999995,
        "direct": true,
        "datetime": "2026-06-11T03:05:08.502235"
      }
    ]
  },
  "XDR-forex": {
    "USD-forex": [
      {
        "name": "OpenExchangeRates",
        "rate": 0.706825,
        "direct": false,
        "datetime": "2026-06-11T03:05:48.908090"
      }
    ]
  }
}