{
  "RUB-bank": {
    "USD-crypto": [
      {
        "name": "Bybit P2P",
        "rate": 78.70657700101324,
        "direct": false,
        "updates_amount": 94
      }
    ],
    "USD-bank": [
      {
        "name": "Cifra RU",
        "rate": 82.85384615384619,
        "direct": false,
        "updates_amount": 39
      },
      {
        "name": "Freedom KZ",
        "rate": 82.29538461538469,
        "direct": false,
        "updates_amount": 39
      }
    ],
    "EUR-bank": [
      {
        "name": "Cifra RU",
        "rate": 97.27948717948723,
        "direct": false,
        "updates_amount": 39
      },
      {
        "name": "Freedom KZ",
        "rate": 96.8192307692307,
        "direct": false,
        "updates_amount": 39
      }
    ],
    "KZT-bank": [
      {
        "name": "Cifra RU",
        "rate": 0.1600512820512821,
        "direct": false,
        "updates_amount": 39
      },
      {
        "name": "Freedom KZ",
        "rate": 6.281538461538464,
        "direct": true,
        "updates_amount": 39
      }
    ],
    "EUR-cash": [
      {
        "name": "Korona Pay",
        "rate": 100.67509076923078,
        "direct": false,
        "updates_amount": 39
      }
    ],
    "RSD-bank": [
      {
        "name": "Visa Payment",
        "rate": 1.2200099483198013,
        "direct": true,
        "updates_amount": 7
      }
    ]
  },
  "USD-crypto": {
    "RUB-bank": [
      {
        "name": "Bybit P2P",
        "rate": 90.7395488721804,
        "direct": true,
        "updates_amount": 95
      }
    ],
    "KZT-bank": [
      {
        "name": "Bybit P2P",
        "rate": 501.3278020050125,
        "direct": true,
        "updates_amount": 95
      }
    ]
  },
  "KZT-bank": {
    "USD-crypto": [
      {
        "name": "Bybit P2P",
        "rate": 517.0197142857143,
        "direct": true,
        "updates_amount": 95
      }
    ],
    "RUB-bank": [
      {
        "name": "Cifra RU",
        "rate": 0.15151282051282053,
        "direct": true,
        "updates_amount": 39
      },
      {
        "name": "Freedom KZ",
        "rate": 6.63153846153846,
        "direct": false,
        "updates_amount": 39
      }
    ],
    "USD-bank": [
      {
        "name": "Freedom KZ",
        "rate": 518.9358974358972,
        "direct": false,
        "updates_amount": 39
      }
    ],
    "EUR-bank": [
      {
        "name": "Freedom KZ",
        "rate": 608.6538461538463,
        "direct": false,
        "updates_amount": 39
      }
    ],
    "RSD-bank": [
      {
        "name": "Visa Payment",
        "rate": 0.19125479427001651,
        "direct": true,
        "updates_amount": 7
      }
    ]
  },
  "USD-forex": {
    "RUB-forex": [
      {
        "name": "MOEX Indicative",
        "rate": 80.25286666666673,
        "direct": true,
        "updates_amount": 39
      },
      {
        "name": "OpenExchangeRates",
        "rate": 79.56496185714286,
        "direct": true,
        "updates_amount": 7
      }
    ],
    "CNY-forex": [
      {
        "name": "OpenExchangeRates",
        "rate": 7.038828571428572,
        "direct": true,
        "updates_amount": 7
      }
    ],
    "KZT-forex": [
      {
        "name": "OpenExchangeRates",
        "rate": 517.1555751428572,
        "direct": true,
        "updates_amount": 7
      }
    ],
    "JPY-forex": [
      {
        "name": "OpenExchangeRates",
        "rate": 157.24572236571427,
        "direct": true,
        "updates_amount": 7
      }
    ],
    "GBP-forex": [
      {
        "name": "OpenExchangeRates",
        "rate": 0.7450482857142856,
        "direct": true,
        "updates_amount": 7
      }
    ],
    "RSD-forex": [
      {
        "name": "OpenExchangeRates",
        "rate": 100.04616814285713,
        "direct": true,
        "updates_amount": 7
      }
    ],
    "EUR-forex": [
      {
        "name": "OpenExchangeRates",
        "rate": 0.8522557142857142,
        "direct": true,
        "updates_amount": 7
      }
    ],
    "XDR-forex": [
      {
        "name": "OpenExchangeRates",
        "rate": 0.6960749999999999,
        "direct": true,
        "updates_amount": 7
      }
    ]
  },
  "RUB-forex": {
    "USD-forex": [
      {
        "name": "MOEX Indicative",
        "rate": 80.25286666666673,
        "direct": false,
        "updates_amount": 39
      },
      {
        "name": "OpenExchangeRates",
        "rate": 79.56496185714286,
        "direct": false,
        "updates_amount": 7
      }
    ],
    "EUR-forex": [
      {
        "name": "MOEX Indicative",
        "rate": 93.9620333333333,
        "direct": false,
        "updates_amount": 39
      }
    ],
    "KZT-forex": [
      {
        "name": "MOEX Indicative",
        "rate": 6.564783453044697,
        "direct": true,
        "updates_amount": 39
      }
    ],
    "GBP-forex": [
      {
        "name": "MOEX Indicative",
        "rate": 107.41146666666668,
        "direct": false,
        "updates_amount": 39
      }
    ],
    "CNY-forex": [
      {
        "name": "MOEX Indicative",
        "rate": 11.214041025641029,
        "direct": false,
        "updates_amount": 39
      }
    ],
    "JPY-forex": [
      {
        "name": "MOEX Indicative",
        "rate": 1.9485989069484668,
        "direct": true,
        "updates_amount": 39
      }
    ]
  },
  "EUR-forex": {
    "RUB-forex": [
      {
        "name": "MOEX Indicative",
        "rate": 93.9620333333333,
        "direct": true,
        "updates_amount": 39
      }
    ],
    "USD-forex": [
      {
        "name": "OpenExchangeRates",
        "rate": 0.8522557142857142,
        "direct": false,
        "updates_amount": 7
      }
    ]
  },
  "KZT-forex": {
    "RUB-forex": [
      {
        "name": "MOEX Indicative",
        "rate": 6.564783453044697,
        "direct": false,
        "updates_amount": 39
      }
    ],
    "USD-forex": [
      {
        "name": "OpenExchangeRates",
        "rate": 517.1555751428572,
        "direct": false,
        "updates_amount": 7
      }
    ]
  },
  "GBP-forex": {
    "RUB-forex": [
      {
        "name": "MOEX Indicative",
        "rate": 107.41146666666668,
        "direct": true,
        "updates_amount": 39
      }
    ],
    "USD-forex": [
      {
        "name": "OpenExchangeRates",
        "rate": 0.7450482857142856,
        "direct": false,
        "updates_amount": 7
      }
    ]
  },
  "CNY-forex": {
    "RUB-forex": [
      {
        "name": "MOEX Indicative",
        "rate": 11.214041025641029,
        "direct": true,
        "updates_amount": 39
      }
    ],
    "USD-forex": [
      {
        "name": "OpenExchangeRates",
        "rate": 7.038828571428572,
        "direct": false,
        "updates_amount": 7
      }
    ]
  },
  "JPY-forex": {
    "RUB-forex": [
      {
        "name": "MOEX Indicative",
        "rate": 1.9485989069484668,
        "direct": false,
        "updates_amount": 39
      }
    ],
    "USD-forex": [
      {
        "name": "OpenExchangeRates",
        "rate": 157.24572236571427,
        "direct": false,
        "updates_amount": 7
      }
    ]
  },
  "USD-bank": {
    "RUB-bank": [
      {
        "name": "Cifra RU",
        "rate": 78.37179487179482,
        "direct": true,
        "updates_amount": 39
      },
      {
        "name": "Freedom KZ",
        "rate": 77.42923076923083,
        "direct": true,
        "updates_amount": 39
      }
    ],
    "KZT-bank": [
      {
        "name": "Freedom KZ",
        "rate": 512.9358974358972,
        "direct": true,
        "updates_amount": 39
      }
    ],
    "EUR-bank": [
      {
        "name": "Freedom KZ",
        "rate": 1.1828743589743589,
        "direct": false,
        "updates_amount": 39
      }
    ],
    "RSD-bank": [
      {
        "name": "Visa Payment",
        "rate": 99.089108506686,
        "direct": true,
        "updates_amount": 7
      }
    ]
  },
  "EUR-bank": {
    "RUB-bank": [
      {
        "name": "Cifra RU",
        "rate": 92.11538461538466,
        "direct": true,
        "updates_amount": 39
      },
      {
        "name": "Freedom KZ",
        "rate": 90.7312820512821,
        "direct": true,
        "updates_amount": 39
      }
    ],
    "KZT-bank": [
      {
        "name": "Freedom KZ",
        "rate": 601.6538461538463,
        "direct": true,
        "updates_amount": 39
      }
    ],
    "USD-bank": [
      {
        "name": "Freedom KZ",
        "rate": 1.1630076923076917,
        "direct": true,
        "updates_amount": 39
      }
    ],
    "RSD-bank": [
      {
        "name": "Visa Payment",
        "rate": 115.95419039543557,
        "direct": true,
        "updates_amount": 7
      }
    ]
  },
  "EUR-cash": {
    "RSD-cash": [
      {
        "name": "Cash Exch",
        "rate": 117.11111111111109,
        "direct": true,
        "updates_amount": 39
      }
    ]
  },
  "RSD-cash": {
    "EUR-cash": [
      {
        "name": "Cash Exch",
        "rate": 118.53333333333336,
        "direct": false,
        "updates_amount": 39
      }
    ],
    "USD-cash": [
      {
        "name": "Cash Exch",
        "rate": 102.09769230769231,
        "direct": false,
        "updates_amount": 39
      }
    ],
    "RUB-cash": [
      {
        "name": "Cash Exch",
        "rate": 1.2899999999999996,
        "direct": false,
        "updates_amount": 39
      }
    ]
  },
  "USD-cash": {
    "RSD-cash": [
      {
        "name": "Cash Exch",
        "rate": 98.0779487179487,
        "direct": true,
        "updates_amount": 39
      }
    ]
  },
  "RUB-cash": {
    "RSD-cash": [
      {
        "name": "Cash Exch",
        "rate": 1.1546153846153833,
        "direct": true,
        "updates_amount": 39
      }
    ]
  },
  "RSD-forex": {
    "USD-forex": [
      {
        "name": "OpenExchangeRates",
        "rate": 100.04616814285713,
        "direct": false,
        "updates_amount": 7
      }
    ]
  },
  "XDR-forex": {
    "USD-forex": [
      {
        "name": "OpenExchangeRates",
        "rate": 0.6960749999999999,
        "direct": false,
        "updates_amount": 7
      }
    ]
  }
}