{
  "USD-forex": {
    "RUB-forex": [
      {
        "name": "MOEX Indicative",
        "rate": 77.89979999999998,
        "direct": true,
        "updates_amount": 18
      },
      {
        "name": "OpenExchangeRates",
        "rate": 78.52386625,
        "direct": true,
        "updates_amount": 4
      }
    ],
    "JPY-forex": [
      {
        "name": "OpenExchangeRates",
        "rate": 155.9247041675,
        "direct": true,
        "updates_amount": 4
      }
    ],
    "RSD-forex": [
      {
        "name": "OpenExchangeRates",
        "rate": 100.416626,
        "direct": true,
        "updates_amount": 4
      }
    ],
    "XDR-forex": [
      {
        "name": "OpenExchangeRates",
        "rate": 0.699294,
        "direct": true,
        "updates_amount": 4
      }
    ],
    "GBP-forex": [
      {
        "name": "OpenExchangeRates",
        "rate": 0.74777925,
        "direct": true,
        "updates_amount": 4
      }
    ],
    "KZT-forex": [
      {
        "name": "OpenExchangeRates",
        "rate": 515.5688195,
        "direct": true,
        "updates_amount": 4
      }
    ],
    "EUR-forex": [
      {
        "name": "OpenExchangeRates",
        "rate": 0.85507875,
        "direct": true,
        "updates_amount": 4
      }
    ],
    "CNY-forex": [
      {
        "name": "OpenExchangeRates",
        "rate": 7.061275000000001,
        "direct": true,
        "updates_amount": 4
      }
    ]
  },
  "RUB-forex": {
    "USD-forex": [
      {
        "name": "MOEX Indicative",
        "rate": 77.89979999999998,
        "direct": false,
        "updates_amount": 18
      },
      {
        "name": "OpenExchangeRates",
        "rate": 78.52386625,
        "direct": false,
        "updates_amount": 4
      }
    ],
    "EUR-forex": [
      {
        "name": "MOEX Indicative",
        "rate": 91.38059999999997,
        "direct": false,
        "updates_amount": 18
      }
    ],
    "KZT-forex": [
      {
        "name": "MOEX Indicative",
        "rate": 6.632630995292056,
        "direct": true,
        "updates_amount": 18
      }
    ],
    "GBP-forex": [
      {
        "name": "MOEX Indicative",
        "rate": 103.5834,
        "direct": false,
        "updates_amount": 18
      }
    ],
    "CNY-forex": [
      {
        "name": "MOEX Indicative",
        "rate": 11.171999999999999,
        "direct": false,
        "updates_amount": 18
      }
    ],
    "JPY-forex": [
      {
        "name": "MOEX Indicative",
        "rate": 2.0130850528434823,
        "direct": true,
        "updates_amount": 18
      }
    ]
  },
  "EUR-forex": {
    "RUB-forex": [
      {
        "name": "MOEX Indicative",
        "rate": 91.38059999999997,
        "direct": true,
        "updates_amount": 18
      }
    ],
    "USD-forex": [
      {
        "name": "OpenExchangeRates",
        "rate": 0.85507875,
        "direct": false,
        "updates_amount": 4
      }
    ]
  },
  "KZT-forex": {
    "RUB-forex": [
      {
        "name": "MOEX Indicative",
        "rate": 6.632630995292056,
        "direct": false,
        "updates_amount": 18
      }
    ],
    "USD-forex": [
      {
        "name": "OpenExchangeRates",
        "rate": 515.5688195,
        "direct": false,
        "updates_amount": 4
      }
    ]
  },
  "GBP-forex": {
    "RUB-forex": [
      {
        "name": "MOEX Indicative",
        "rate": 103.5834,
        "direct": true,
        "updates_amount": 18
      }
    ],
    "USD-forex": [
      {
        "name": "OpenExchangeRates",
        "rate": 0.74777925,
        "direct": false,
        "updates_amount": 4
      }
    ]
  },
  "CNY-forex": {
    "RUB-forex": [
      {
        "name": "MOEX Indicative",
        "rate": 11.171999999999999,
        "direct": true,
        "updates_amount": 18
      }
    ],
    "USD-forex": [
      {
        "name": "OpenExchangeRates",
        "rate": 7.061275000000001,
        "direct": false,
        "updates_amount": 4
      }
    ]
  },
  "JPY-forex": {
    "RUB-forex": [
      {
        "name": "MOEX Indicative",
        "rate": 2.0130850528434823,
        "direct": false,
        "updates_amount": 18
      }
    ],
    "USD-forex": [
      {
        "name": "OpenExchangeRates",
        "rate": 155.9247041675,
        "direct": false,
        "updates_amount": 4
      }
    ]
  },
  "RUB-bank": {
    "USD-crypto": [
      {
        "name": "Bybit P2P",
        "rate": 77.46459979736574,
        "direct": false,
        "updates_amount": 47
      }
    ],
    "USD-bank": [
      {
        "name": "Cifra RU",
        "rate": 81.70000000000002,
        "direct": false,
        "updates_amount": 18
      },
      {
        "name": "Freedom KZ",
        "rate": 81.4727777777778,
        "direct": false,
        "updates_amount": 18
      }
    ],
    "EUR-bank": [
      {
        "name": "Cifra RU",
        "rate": 94.93333333333331,
        "direct": false,
        "updates_amount": 18
      },
      {
        "name": "Freedom KZ",
        "rate": 95.06277777777775,
        "direct": false,
        "updates_amount": 18
      }
    ],
    "KZT-bank": [
      {
        "name": "Cifra RU",
        "rate": 0.1573333333333333,
        "direct": false,
        "updates_amount": 18
      },
      {
        "name": "Freedom KZ",
        "rate": 6.409444444444446,
        "direct": true,
        "updates_amount": 18
      }
    ],
    "EUR-cash": [
      {
        "name": "Korona Pay",
        "rate": 98.33191666666669,
        "direct": false,
        "updates_amount": 18
      }
    ],
    "RSD-bank": [
      {
        "name": "Visa Payment",
        "rate": 1.2719981549363955,
        "direct": true,
        "updates_amount": 4
      }
    ]
  },
  "USD-crypto": {
    "RUB-bank": [
      {
        "name": "Bybit P2P",
        "rate": 89.14215805471126,
        "direct": true,
        "updates_amount": 47
      }
    ],
    "KZT-bank": [
      {
        "name": "Bybit P2P",
        "rate": 501.69003039513694,
        "direct": true,
        "updates_amount": 47
      }
    ]
  },
  "KZT-bank": {
    "USD-crypto": [
      {
        "name": "Bybit P2P",
        "rate": 523.7292097264439,
        "direct": true,
        "updates_amount": 47
      }
    ],
    "RUB-bank": [
      {
        "name": "Cifra RU",
        "rate": 0.1493333333333333,
        "direct": true,
        "updates_amount": 18
      },
      {
        "name": "Freedom KZ",
        "rate": 6.759444444444444,
        "direct": false,
        "updates_amount": 18
      }
    ],
    "USD-bank": [
      {
        "name": "Freedom KZ",
        "rate": 523.2222222222222,
        "direct": false,
        "updates_amount": 18
      }
    ],
    "EUR-bank": [
      {
        "name": "Freedom KZ",
        "rate": 609.2777777777778,
        "direct": false,
        "updates_amount": 18
      }
    ],
    "RSD-bank": [
      {
        "name": "Visa Payment",
        "rate": 0.19266117220258813,
        "direct": true,
        "updates_amount": 4
      }
    ]
  },
  "USD-bank": {
    "RUB-bank": [
      {
        "name": "Cifra RU",
        "rate": 77.28333333333333,
        "direct": true,
        "updates_amount": 18
      },
      {
        "name": "Freedom KZ",
        "rate": 76.44833333333332,
        "direct": true,
        "updates_amount": 18
      }
    ],
    "KZT-bank": [
      {
        "name": "Freedom KZ",
        "rate": 516.2222222222222,
        "direct": true,
        "updates_amount": 18
      }
    ],
    "EUR-bank": [
      {
        "name": "Freedom KZ",
        "rate": 1.1768277777777774,
        "direct": false,
        "updates_amount": 18
      }
    ],
    "RSD-bank": [
      {
        "name": "Visa Payment",
        "rate": 99.79455435144749,
        "direct": true,
        "updates_amount": 4
      }
    ]
  },
  "EUR-bank": {
    "RUB-bank": [
      {
        "name": "Cifra RU",
        "rate": 90.14444444444443,
        "direct": true,
        "updates_amount": 18
      },
      {
        "name": "Freedom KZ",
        "rate": 89.10555555555555,
        "direct": true,
        "updates_amount": 18
      }
    ],
    "KZT-bank": [
      {
        "name": "Freedom KZ",
        "rate": 602.2777777777778,
        "direct": true,
        "updates_amount": 18
      }
    ],
    "USD-bank": [
      {
        "name": "Freedom KZ",
        "rate": 1.1568277777777771,
        "direct": true,
        "updates_amount": 18
      }
    ],
    "RSD-bank": [
      {
        "name": "Visa Payment",
        "rate": 115.94640015168939,
        "direct": true,
        "updates_amount": 4
      }
    ]
  },
  "RSD-forex": {
    "USD-forex": [
      {
        "name": "OpenExchangeRates",
        "rate": 100.416626,
        "direct": false,
        "updates_amount": 4
      }
    ]
  },
  "XDR-forex": {
    "USD-forex": [
      {
        "name": "OpenExchangeRates",
        "rate": 0.699294,
        "direct": false,
        "updates_amount": 4
      }
    ]
  }
}