{
  "USD-forex": {
    "RUB-forex": [
      {
        "name": "MOEX Indicative",
        "rate": 78.2267,
        "direct": true,
        "updates_amount": 9
      },
      {
        "name": "OpenExchangeRates",
        "rate": 80.49776499999999,
        "direct": true,
        "updates_amount": 2
      }
    ],
    "KZT-forex": [
      {
        "name": "OpenExchangeRates",
        "rate": 510.423137,
        "direct": true,
        "updates_amount": 2
      }
    ],
    "CNY-forex": [
      {
        "name": "OpenExchangeRates",
        "rate": 6.982049999999999,
        "direct": true,
        "updates_amount": 2
      }
    ],
    "XDR-forex": [
      {
        "name": "OpenExchangeRates",
        "rate": 0.69877,
        "direct": true,
        "updates_amount": 2
      }
    ],
    "JPY-forex": [
      {
        "name": "OpenExchangeRates",
        "rate": 157.12465625,
        "direct": true,
        "updates_amount": 2
      }
    ],
    "GBP-forex": [
      {
        "name": "OpenExchangeRates",
        "rate": 0.744355,
        "direct": true,
        "updates_amount": 2
      }
    ],
    "RSD-forex": [
      {
        "name": "OpenExchangeRates",
        "rate": 100.6370235,
        "direct": true,
        "updates_amount": 2
      }
    ],
    "EUR-forex": [
      {
        "name": "OpenExchangeRates",
        "rate": 0.8580075,
        "direct": true,
        "updates_amount": 2
      }
    ]
  },
  "RUB-forex": {
    "USD-forex": [
      {
        "name": "MOEX Indicative",
        "rate": 78.2267,
        "direct": false,
        "updates_amount": 9
      },
      {
        "name": "OpenExchangeRates",
        "rate": 80.49776499999999,
        "direct": false,
        "updates_amount": 2
      }
    ],
    "EUR-forex": [
      {
        "name": "MOEX Indicative",
        "rate": 92.0938,
        "direct": false,
        "updates_amount": 9
      }
    ],
    "KZT-forex": [
      {
        "name": "MOEX Indicative",
        "rate": 6.527415143603134,
        "direct": true,
        "updates_amount": 9
      }
    ],
    "GBP-forex": [
      {
        "name": "MOEX Indicative",
        "rate": 105.606,
        "direct": false,
        "updates_amount": 9
      }
    ],
    "CNY-forex": [
      {
        "name": "MOEX Indicative",
        "rate": 11.315,
        "direct": false,
        "updates_amount": 9
      }
    ],
    "JPY-forex": [
      {
        "name": "MOEX Indicative",
        "rate": 1.998041918919459,
        "direct": true,
        "updates_amount": 9
      }
    ]
  },
  "EUR-forex": {
    "RUB-forex": [
      {
        "name": "MOEX Indicative",
        "rate": 92.0938,
        "direct": true,
        "updates_amount": 9
      }
    ],
    "USD-forex": [
      {
        "name": "OpenExchangeRates",
        "rate": 0.8580075,
        "direct": false,
        "updates_amount": 2
      }
    ]
  },
  "KZT-forex": {
    "RUB-forex": [
      {
        "name": "MOEX Indicative",
        "rate": 6.527415143603134,
        "direct": false,
        "updates_amount": 9
      }
    ],
    "USD-forex": [
      {
        "name": "OpenExchangeRates",
        "rate": 510.423137,
        "direct": false,
        "updates_amount": 2
      }
    ]
  },
  "GBP-forex": {
    "RUB-forex": [
      {
        "name": "MOEX Indicative",
        "rate": 105.606,
        "direct": true,
        "updates_amount": 9
      }
    ],
    "USD-forex": [
      {
        "name": "OpenExchangeRates",
        "rate": 0.744355,
        "direct": false,
        "updates_amount": 2
      }
    ]
  },
  "CNY-forex": {
    "RUB-forex": [
      {
        "name": "MOEX Indicative",
        "rate": 11.315,
        "direct": true,
        "updates_amount": 9
      }
    ],
    "USD-forex": [
      {
        "name": "OpenExchangeRates",
        "rate": 6.982049999999999,
        "direct": false,
        "updates_amount": 2
      }
    ]
  },
  "JPY-forex": {
    "RUB-forex": [
      {
        "name": "MOEX Indicative",
        "rate": 1.998041918919459,
        "direct": false,
        "updates_amount": 9
      }
    ],
    "USD-forex": [
      {
        "name": "OpenExchangeRates",
        "rate": 157.12465625,
        "direct": false,
        "updates_amount": 2
      }
    ]
  },
  "RUB-bank": {
    "USD-crypto": [
      {
        "name": "Bybit P2P",
        "rate": 80.0901407867495,
        "direct": false,
        "updates_amount": 23
      }
    ],
    "USD-bank": [
      {
        "name": "Cifra RU",
        "rate": 83.29999999999998,
        "direct": false,
        "updates_amount": 9
      },
      {
        "name": "Freedom KZ",
        "rate": 83.29999999999998,
        "direct": false,
        "updates_amount": 9
      }
    ],
    "EUR-bank": [
      {
        "name": "Cifra RU",
        "rate": 97.29999999999998,
        "direct": false,
        "updates_amount": 9
      },
      {
        "name": "Freedom KZ",
        "rate": 97.24,
        "direct": false,
        "updates_amount": 9
      }
    ],
    "KZT-bank": [
      {
        "name": "Cifra RU",
        "rate": 0.1635,
        "direct": false,
        "updates_amount": 9
      },
      {
        "name": "Freedom KZ",
        "rate": 6.170000000000001,
        "direct": true,
        "updates_amount": 9
      }
    ],
    "EUR-cash": [
      {
        "name": "Korona Pay",
        "rate": 100.93675155555555,
        "direct": false,
        "updates_amount": 9
      }
    ],
    "RSD-bank": [
      {
        "name": "Visa Payment",
        "rate": 1.234861758848088,
        "direct": true,
        "updates_amount": 2
      }
    ]
  },
  "USD-crypto": {
    "RUB-bank": [
      {
        "name": "Bybit P2P",
        "rate": 88.20124223602484,
        "direct": true,
        "updates_amount": 23
      }
    ],
    "KZT-bank": [
      {
        "name": "Bybit P2P",
        "rate": 476.98322981366454,
        "direct": true,
        "updates_amount": 23
      }
    ]
  },
  "KZT-bank": {
    "USD-crypto": [
      {
        "name": "Bybit P2P",
        "rate": 512.015652173913,
        "direct": true,
        "updates_amount": 23
      }
    ],
    "RUB-bank": [
      {
        "name": "Cifra RU",
        "rate": 0.1549,
        "direct": true,
        "updates_amount": 9
      },
      {
        "name": "Freedom KZ",
        "rate": 6.519999999999998,
        "direct": false,
        "updates_amount": 9
      }
    ],
    "USD-bank": [
      {
        "name": "Freedom KZ",
        "rate": 515.0,
        "direct": false,
        "updates_amount": 9
      }
    ],
    "EUR-bank": [
      {
        "name": "Freedom KZ",
        "rate": 600.0,
        "direct": false,
        "updates_amount": 9
      }
    ],
    "RSD-bank": [
      {
        "name": "Visa Payment",
        "rate": 0.1951053491286044,
        "direct": true,
        "updates_amount": 2
      }
    ]
  },
  "USD-bank": {
    "RUB-bank": [
      {
        "name": "Cifra RU",
        "rate": 78.20000000000002,
        "direct": true,
        "updates_amount": 9
      },
      {
        "name": "Freedom KZ",
        "rate": 77.99,
        "direct": true,
        "updates_amount": 9
      }
    ],
    "KZT-bank": [
      {
        "name": "Freedom KZ",
        "rate": 508.0,
        "direct": true,
        "updates_amount": 9
      }
    ],
    "EUR-bank": [
      {
        "name": "Freedom KZ",
        "rate": 1.1775999999999998,
        "direct": false,
        "updates_amount": 9
      }
    ],
    "RSD-bank": [
      {
        "name": "Visa Payment",
        "rate": 99.55445597880158,
        "direct": true,
        "updates_amount": 2
      }
    ]
  },
  "EUR-bank": {
    "RUB-bank": [
      {
        "name": "Cifra RU",
        "rate": 92.04999999999998,
        "direct": true,
        "updates_amount": 9
      },
      {
        "name": "Freedom KZ",
        "rate": 90.95000000000002,
        "direct": true,
        "updates_amount": 9
      }
    ],
    "KZT-bank": [
      {
        "name": "Freedom KZ",
        "rate": 593.0,
        "direct": true,
        "updates_amount": 9
      }
    ],
    "USD-bank": [
      {
        "name": "Freedom KZ",
        "rate": 1.1576,
        "direct": true,
        "updates_amount": 9
      }
    ],
    "RSD-bank": [
      {
        "name": "Visa Payment",
        "rate": 115.90141309900385,
        "direct": true,
        "updates_amount": 2
      }
    ]
  },
  "EUR-cash": {
    "RSD-cash": [
      {
        "name": "Cash Exch",
        "rate": 116.75999999999999,
        "direct": true,
        "updates_amount": 9
      }
    ]
  },
  "RSD-cash": {
    "EUR-cash": [
      {
        "name": "Cash Exch",
        "rate": 118.38000000000001,
        "direct": false,
        "updates_amount": 9
      }
    ],
    "USD-cash": [
      {
        "name": "Cash Exch",
        "rate": 102.20714285714288,
        "direct": false,
        "updates_amount": 9
      }
    ],
    "RUB-cash": [
      {
        "name": "Cash Exch",
        "rate": 1.3100000000000003,
        "direct": false,
        "updates_amount": 9
      }
    ]
  },
  "USD-cash": {
    "RSD-cash": [
      {
        "name": "Cash Exch",
        "rate": 98.3714285714286,
        "direct": true,
        "updates_amount": 9
      }
    ]
  },
  "RUB-cash": {
    "RSD-cash": [
      {
        "name": "Cash Exch",
        "rate": 1.13,
        "direct": true,
        "updates_amount": 9
      }
    ]
  },
  "XDR-forex": {
    "USD-forex": [
      {
        "name": "OpenExchangeRates",
        "rate": 0.69877,
        "direct": false,
        "updates_amount": 2
      }
    ]
  },
  "RSD-forex": {
    "USD-forex": [
      {
        "name": "OpenExchangeRates",
        "rate": 100.6370235,
        "direct": false,
        "updates_amount": 2
      }
    ]
  }
}